{
    "contracts": {
        "A": {
            "rotation": {
                "D": [
                    "E"
                ],
                "L": [
                    "E",
                    "D"
                ],
                "N": [
                    "E",
                    "D",
                    "L"
                ]
            },
            "max_workload": 2160,
            "stretchs": {
                "max_on": 5,
                "min_on": 2,
                "min_off": 2
            },
            "weekends": 1,
            "max_shifts": {
                "N": 2
            }
        },
        "AE": {
            "rotation": {
                "D": [
                    "E"
                ],
                "L": [
                    "E",
                    "D"
                ],
                "N": [
                    "E",
                    "D",
                    "L"
                ]
            },
            "max_workload": 2025,
            "stretchs": {
                "max_on": 4,
                "min_on": 2,
                "min_off": 2
            },
            "weekends": 1,
            "max_shifts": {
                "N": 2
            }
        },
        "B": {
            "rotation": {
                "D": [
                    "E"
                ],
                "L": [
                    "E",
                    "D"
                ],
                "N": [
                    "E",
                    "D",
                    "L"
                ]
            },
            "max_workload": 2160,
            "stretchs": {
                "max_on": 5,
                "min_on": 2,
                "min_off": 2
            },
            "weekends": 1,
            "max_shifts": {
                "D": 0,
                "N": 0
            }
        },
        "C": {
            "rotation": {
                "D": [
                    "E"
                ],
                "L": [
                    "E",
                    "D"
                ],
                "N": [
                    "E",
                    "D",
                    "L"
                ]
            },
            "max_workload": 2160,
            "stretchs": {
                "max_on": 5,
                "min_on": 2,
                "min_off": 2
            },
            "weekends": 1,
            "max_shifts": {
                "L": 0,
                "N": 2
            }
        },
        "D": {
            "rotation": {
                "D": [
                    "E"
                ],
                "L": [
                    "E",
                    "D"
                ],
                "N": [
                    "E",
                    "D",
                    "L"
                ]
            },
            "max_workload": 2160,
            "stretchs": {
                "max_on": 5,
                "min_on": 2,
                "min_off": 2
            },
            "weekends": 1,
            "max_shifts": {
                "N": 0
            }
        },
        "G": {
            "rotation": {
                "D": [
                    "E"
                ],
                "L": [
                    "E",
                    "D"
                ],
                "N": [
                    "E",
                    "D",
                    "L"
                ]
            },
            "max_workload": 2160,
            "stretchs": {
                "max_on": 5,
                "min_on": 2,
                "min_off": 2
            },
            "weekends": 1,
            "max_shifts": {
                "D": 0,
                "N": 2
            }
        },
        "I": {
            "rotation": {
                "D": [
                    "E"
                ],
                "L": [
                    "E",
                    "D"
                ],
                "N": [
                    "E",
                    "D",
                    "L"
                ]
            },
            "max_workload": 2160,
            "stretchs": {
                "max_on": 5,
                "min_on": 2,
                "min_off": 2
            },
            "weekends": 1,
            "max_shifts": {
                "L": 0,
                "N": 0
            }
        },
        "O": {
            "rotation": {
                "D": [
                    "E"
                ],
                "L": [
                    "E",
                    "D"
                ],
                "N": [
                    "E",
                    "D",
                    "L"
                ]
            },
            "max_workload": 2160,
            "stretchs": {
                "max_on": 5,
                "min_on": 2,
                "min_off": 2
            },
            "weekends": 1,
            "max_shifts": {
                "D": 0,
                "L": 0,
                "N": 2
            }
        },
        "P": {
            "rotation": {
                "D": [
                    "E"
                ],
                "L": [
                    "E",
                    "D"
                ],
                "N": [
                    "E",
                    "D",
                    "L"
                ]
            },
            "max_workload": 2160,
            "stretchs": {
                "max_on": 5,
                "min_on": 2,
                "min_off": 2
            },
            "weekends": 1,
            "max_shifts": {
                "E": 0,
                "N": 2
            }
        }
    },
    "shifts_length": {
        "D": 480,
        "E": 480,
        "L": 480,
        "N": 480
    }
}